fractal_categorizer/__init__.py
fractal_categorizer/main.py
fractal_categorizer/prompts.py
fractal_categorizer-2025.12.21180718.dist-info/METADATA
fractal_categorizer-2025.12.21180718.dist-info/WHEEL
fractal_categorizer-2025.12.21180718.dist-info/top_level.txt
fractal_categorizer-2025.12.21180718.dist-info/RECORD
