Metadata-Version: 2.4
Name: fractal-categorizer
Version: 2025.12.21180718
Summary: A new package that processes user-provided text descriptions of fractal patterns, cellular automata configurations, or similar generative systems, and returns structured analyses or classifications. F
Author-email: fractal-categorizer <hi@eugene.plus>
License: MIT
Project-URL: Homepage, https://github.com/chigwell/fractal-categorizer
Requires-Python: >=3.9
Requires-Dist: langchain-llm7>=0.0.0
Requires-Dist: llmatch-messages>=0.0.0
Requires-Dist: langchain-core>=0.3.0
